{"cameraMode":{"drawMode":0,"name":"Shaded","section":"Shading Mode"},"sceneLighting":false,"audioPlay":false,"sceneViewState":{"showFog":true,"showMaterialUpdate":false,"showSkybox":false,"showFlares":true,"showImageEffects":true,"showParticleSystems":true,"showVisualEffectGraphs":true,"m_FxEnabled":true},"in2DMode":false,"pivot":{"x":10.0,"y":2.049745798110962,"z":9.931722640991211},"rotation":{"x":0.10882452875375748,"y":-0.7240697741508484,"z":0.11745210736989975,"w":0.6708893775939941},"size":4.659463882446289,"orthographic":false}